jiayihn_equipment_mcp/__init__.py
jiayihn_equipment_mcp/equipment__mcp_server.py
jiayihn_equipment_mcp-0.1.3.dist-info/METADATA
jiayihn_equipment_mcp-0.1.3.dist-info/WHEEL
jiayihn_equipment_mcp-0.1.3.dist-info/entry_points.txt
jiayihn_equipment_mcp-0.1.3.dist-info/RECORD
