Metadata-Version: 2.4
Name: jiayihn-equipment-mcp
Version: 0.1.3
Summary: Add your description here
Author-email: xiechen <xiechen@jiayihn.net>
Requires-Python: >=3.10
Requires-Dist: httpx>=0.28.1
Requires-Dist: mcp[cli]>=1.9.4
